LICENSE
MANIFEST.in
README.md
requirements.txt
setup.py
csdn/__init__.py
csdn/__main__.py
csdn/csdn.py
csdn.egg-info/PKG-INFO
csdn.egg-info/SOURCES.txt
csdn.egg-info/dependency_links.txt
csdn.egg-info/entry_points.txt
csdn.egg-info/requires.txt
csdn.egg-info/top_level.txt
csdn/csdn_backup/__init__.py
csdn/csdn_backup/csdn_backup.py
csdn/csdn_backup/csdn_backup_common.py
csdn/csdn_backup/csdn_backup_requests.py
csdn/csdn_backup/csdn_backup_selenium.py
csdn/csdn_offline/__init__.py
csdn/csdn_offline/csdn_offline.py
csdn/csdn_offline/csdn_offline_aiohttp.py
csdn/csdn_offline/csdn_offline_common.py