Metadata-Version: 1.1
Name: csdn
Version: 1.1.1
Summary: csdn blog backup or offline.
Home-page: https://github.com/minghu6/csdn
Author: minghu6
Author-email: a19678zy@163.com
License: BSD License
Platform: UNKNOWN
Classifier: Intended Audience :: Developers
Classifier: License :: OSI Approved :: BSD License
Classifier: Operating System :: OS Independent
Classifier: Programming Language :: Python
Classifier: Programming Language :: Python :: 3
